graphcoltests/__init__.py
graphcoltests/gulosos.py
graphcoltests/metaheuristicas.py
graphcoltests/visual.py
graphcoltests-0.1.1.dist-info/WHEEL
graphcoltests-0.1.1.dist-info/METADATA
graphcoltests-0.1.1.dist-info/RECORD
